README.rst
setup.py
gtmem/__init__.py
gtmem/command_line.py
gtmem.egg-info/PKG-INFO
gtmem.egg-info/SOURCES.txt
gtmem.egg-info/dependency_links.txt
gtmem.egg-info/entry_points.txt
gtmem.egg-info/requires.txt
gtmem.egg-info/top_level.txt