Metadata-Version: 1.2
Name: gtmem
Version: 0.6.2
Summary: Google Takeout importer for Memair
Home-page: https://github.com/memair/google-takeout-impoter
Author: Greg Clarke
Author-email: greg@gho.st
License: MIT
Keywords: memair,quantified self,extended mind,lifelogging
Platform: UNKNOWN
Classifier: Development Status :: 4 - Beta
Classifier: Intended Audience :: Developers
Classifier: Topic :: Software Development :: Build Tools
Classifier: License :: OSI Approved :: MIT License
Classifier: Programming Language :: Python
Requires-Python: >=3
